salud/PolarityAnalyzer.py
salud/__init__.py
salud/__main__.py
salud-2.4.2020.dist-info/METADATA
salud-2.4.2020.dist-info/WHEEL
salud-2.4.2020.dist-info/entry_points.txt
salud-2.4.2020.dist-info/top_level.txt
salud-2.4.2020.dist-info/RECORD
