Metadata-Version: 2.1
Name: salud
Version: 2.4.2020
Summary: Internal PyPi package for mdbrd
Home-page: https://github.com/moodboard/salud
Author: Moodboard Webmaster
Author-email: webmaster@mdbrd.in
License: UNKNOWN
Platform: UNKNOWN
Classifier: Programming Language :: Python :: 3.7
Requires-Dist: vaderSentiment
Requires-Dist: nltk
Requires-Dist: emoji
Requires-Dist: textblob
